LICENSE
README.md
setup.cfg
setup.py
mfpy/__init__.py
mfpy/__main__.py
mfpy/mf.py
mfpy/model.py
mfpy.egg-info/PKG-INFO
mfpy.egg-info/SOURCES.txt
mfpy.egg-info/dependency_links.txt
mfpy.egg-info/requires.txt
mfpy.egg-info/top_level.txt