Metadata-Version: 2.1
Name: mfpy
Version: 0.1.1
Summary: MoneyForward クラウド勤怠といい感じに通信していい感じに打刻するやつ
Home-page: https://github.com/puhitaku/mfpy
Author: Takumi Sueda
Author-email: puhitaku@gmail.com
License: UNKNOWN
Platform: UNKNOWN
Classifier: Development Status :: 4 - Beta
Classifier: License :: OSI Approved :: MIT License
Classifier: Programming Language :: Python :: 3
Classifier: Programming Language :: Python :: 3.7
Classifier: Programming Language :: Python :: 3.8
Classifier: Programming Language :: Python :: 3.9
Classifier: Topic :: Utilities
Requires-Python: >=3.6
